tkinter_spa/_version.py
tkinter_spa/cli.py
tkinter_spa/main_frame.py
tkinter_spa/surveyor.py
tkinter_spa/tk_root.py
tkinter_spa/view.py
tkinter_spa/utils/debugging.py
tkinter_spa/utils/path_tools.py
tkinter_spa/utils/string_tools.py
tkinter_spa/utils/tkinter_tools.py
tkinter_spa-1.0.0.dist-info/licenses/LICENCE
tkinter_spa-1.0.0.dist-info/METADATA
tkinter_spa-1.0.0.dist-info/WHEEL
tkinter_spa-1.0.0.dist-info/entry_points.txt
tkinter_spa-1.0.0.dist-info/top_level.txt
tkinter_spa-1.0.0.dist-info/RECORD
