Metadata-Version: 2.4
Name: tkinter_spa
Version: 1.0.0
Summary: A Single Page Application framework for Tkinter
Author: wbarillon
License-Expression: MIT
Project-URL: Source, https://gitlab.com/wbarillon/tkinter_spa
Project-URL: Documentation, https://wbarillon.gitlab.io/tkinter_spa
Classifier: Development Status :: 5 - Production/Stable
Classifier: Intended Audience :: Developers
Classifier: Operating System :: OS Independent
Classifier: Programming Language :: Python :: 3
Classifier: Topic :: Software Development :: Libraries :: Application Frameworks
Requires-Python: >=3.6
License-File: LICENCE
Dynamic: license-file
